djangoHexadecimal/__init__.py
djangoHexadecimal/fields.py
DjangoHexadecimalField-0.0.3.dist-info/LICENSE
DjangoHexadecimalField-0.0.3.dist-info/METADATA
DjangoHexadecimalField-0.0.3.dist-info/WHEEL
DjangoHexadecimalField-0.0.3.dist-info/top_level.txt
DjangoHexadecimalField-0.0.3.dist-info/RECORD
