Metadata-Version: 2.1
Name: DjangoHexadecimalField
Version: 0.0.3
Summary: Hexadecimal Field for Django
Home-page: https://github.com/mathrithms/Django-Hexadecimal-Field
Author: mathrithms
Author-email: hello@mathrithms.com
License: UNKNOWN
Platform: UNKNOWN
Classifier: Programming Language :: Python :: 3
Classifier: License :: OSI Approved :: MIT License
Classifier: Operating System :: OS Independent
Requires-Dist: Django
